{
  "project_info": {
    "project_number": "147074606604",
    "project_id": "chatapp-4fc36",
    "storage_bucket": "chatapp-4fc36.appspot.com"
  },
  "client": [
    {
      "client_info": {
        "mobilesdk_app_id": "1:147074606604:android:d68b330bc03e77e36bf029",
        "android_client_info": {
          "package_name": "com.chatapp"
        }
      },
      "oauth_client": [
        {
          "client_id": "147074606604-3frg90qi0ehb9a61fom5afroarrdo4ej.apps.googleusercontent.com",
          "client_type": 3
        }
      ],
      "api_key": [
        {
          "current_key": "AIzaSyCQSKs1q7beUT_f2HXa_I5pJqtXpUTYNAE"
        }
      ],
      "services": {
        "appinvite_service": {
          "other_platform_oauth_client": [
            {
              "client_id": "147074606604-3frg90qi0ehb9a61fom5afroarrdo4ej.apps.googleusercontent.com",
              "client_type": 3
            }
          ]
        }
      }
    }
  ],
  "configuration_version": "1"
}